{"stem":"13.11","instances":[{"docUri":"1746atlantik.html","score":2,"contexts":[{"form":"13.11","weight":"1","pos":106,"context":"...10.11.1746  11.11.1746  12.11.1746  <mark>13.11<\/mark>.1746  14.11.1746  15.11.1746  16.11...","fid":"main2"},{"form":"13.11","weight":"1","pos":641,"context":"Datum: <mark>13.11<\/mark>.1746 Position: Lat: 23°5' Long:...","fid":"positionPopup27","in":["ssCtx2"]}]},{"docUri":"1752.html","score":1,"contexts":[{"form":"13.11","weight":"1","pos":144,"context":"...10.11.1752 11.11.1752 12.11.1752 <mark>13.11<\/mark>.1752 14.11.1752 15.11.1752 16.11...","fid":"main2"}]}]}