{"stem":"anhaltende","instances":[{"docUri":"1761atlantik.html","score":2,"contexts":[{"form":"anhaltende","weight":"1","pos":1398,"context":"...(d. 3ten seit gestern früh hörte zwar der <mark>anhaltende<\/mark> Calm auf, dennoch musten wir bis 4 Uhr Nachmittags...","fid":"diaryPopup22","in":["ssCtx2"]},{"form":"anhaltende","weight":"1","pos":1547,"context":"...40 Grad Latit., ob wir gleich durch beständig <mark>anhaltende<\/mark> contraire Winde in den 5 Wochen nicht viel über...","fid":"diaryPopup27","in":["ssCtx2"]}]}]}