{"stem":"ausgespannt","instances":[{"docUri":"1761land.html","score":2,"contexts":[{"form":"ausgespannt","weight":"1","pos":2079,"context":"...Pferde waren, davon aber 2 vor der Stadt <mark>ausgespannt<\/mark> werden sollten. Von Helmstädt über Königslutter, wo...","fid":"diaryPopup14","in":["ssCtx2"]},{"form":"ausgespannt","weight":"1","pos":2146,"context":"...Uhr abends vor Braunschweig an, unsere 6 Pferde wurden <mark>ausgespannt<\/mark>, u. der besagte Postillion fuhr uns mit seinen...","fid":"diaryPopup14","in":["ssCtx2"]}]}]}