{"stem":"begleitet","instances":[{"docUri":"1753kanal.html","score":1,"contexts":[{"form":"begleitet","weight":"1","pos":174,"context":"...nahmen wir zärtlichen Abschied von den Geschwistern die uns <mark>begleitet<\/mark> hatten, und richteten uns um ein auf unsre weitern...","fid":"diaryPopup1","in":["ssCtx2"]}]},{"docUri":"1752.html","score":1,"contexts":[{"form":"begleitet","weight":"1","pos":781,"context":"...und danckbar vor daß, daß er uns biß hierher <mark>begleitet<\/mark> hat, und es wird ihm als ein großes...","fid":"diaryPopup5","in":["ssCtx2"]}]},{"docUri":"1746atlantik.html","score":1,"contexts":[{"form":"begleitet","weight":"1","pos":4449,"context":"...ihr seelgen Leut uns jezt zwar unerblicklich Eur Geist <mark>begleitet<\/mark> uns auch heut und das macht uns so glücklich...","fid":"diaryPopup14","in":["ssCtx2"]}]},{"docUri":"1761kanal.html","score":1,"contexts":[{"form":"begleitet","weight":"1","pos":3329,"context":"...Unsre Singstde war mit einer merkℓn Nähe des Freundes <mark>begleitet<\/mark>.","fid":"diaryPopup10","in":["ssCtx2"]}]}]}