{"stem":"besondere","instances":[{"docUri":"1749atlantik.html","score":2,"contexts":[{"form":"besondere","weight":"1","pos":449,"context":"...- Gefühle u. einer Music wobey ihm einige gantz <mark>besondere<\/mark> Versel gesungen wurden. ","fid":"diaryPopup8"},{"form":"besondere","weight":"1","pos":4198,"context":"...zärtlichen Bedenken vor dem Lämmlein vor meine Person ins <mark>besondere<\/mark>. Und bin mit einem demüthigen Handkuß euer armes...","fid":"diaryPopup54"}]},{"docUri":"1746atlantik.html","score":1,"contexts":[{"form":"besondere","weight":"1","pos":12127,"context":"...zu bringen. Wir sahen doch unter allem seine <mark>besondere<\/mark> Hand über uns, und daß Er obgleich dieser...","fid":"diaryPopup66","in":["ssCtx2"]}]}]}