{"stem":"bestimmt","instances":[{"docUri":"1753kanal.html","score":1,"contexts":[{"form":"bestimmt","weight":"1","pos":136,"context":"...in London angekommen waren welche mit dem Schiff Irene <mark>bestimmt<\/mark> waren nach America zu gehen, so hatten sie...","fid":"diaryPopup1"}]},{"docUri":"einleitung.html","score":1,"contexts":[{"form":"bestimmt","weight":"1","pos":219,"context":"...deren Mitglieder für die pennsylvanischen Gemeinorte Nazareth und Bethlehem <mark>bestimmt<\/mark> waren, über den Atlantik. Seit 1748 besaß...","in":["ssCtx1"]}]},{"docUri":"datenschutz.html","score":1,"contexts":[{"form":"bestimmt","weight":"1","pos":343,"context":"...Geltung des Schweizer DSG weiterhin nach dem Schweizer DSG <mark>bestimmt<\/mark>.","in":["ssCtx1"]}]}]}