{"stem":"braut","instances":[{"docUri":"1761kanal.html","score":2,"contexts":[{"form":"Braut","weight":"1","pos":2327,"context":"...am 15ten Febr. u. sangen Abends den <mark>Braut<\/mark>-Gesang.","fid":"diaryPopup8"},{"form":"Braut","weight":"1","pos":2443,"context":"...zu bekommen. Abends nach der Liturgie: Die <mark>Braut<\/mark> spricht zu dem Manne, machte Br. Nathanael den...","fid":"diaryPopup8"}]},{"docUri":"1746kanal.html","score":1,"contexts":[{"form":"Braut","weight":"1","pos":349,"context":"...was dir dein Mann vertraut von dem Geheimniß seiner <mark>Braut<\/mark> und instillir uns immer was von deinem neuen gratias...","fid":"diaryPopup1","in":["ssCtx2"]}]}]}