{"stem":"captain","instances":[{"docUri":"1746.html","score":1,"contexts":[{"form":"Captain","weight":"1","pos":68,"context":"<mark>Captain<\/mark> Crosswaite"}]},{"docUri":"einleitung.html","score":1,"contexts":[{"form":"Captain","weight":"1","pos":266,"context":"...: Ts – Bd.2.1.  Abb. 2: <mark>Captain<\/mark> Nicholas Garrison (1701-1781); © Archiv...","in":["ssCtx1"]}]},{"docUri":"1761kanal.html","score":1,"contexts":[{"form":"Captain","weight":"1","pos":767,"context":"..., u. nun wieder zurückgeht. Er fragte unsern <mark>Captain<\/mark>, ob er nicht Mährℓ. Brr. am...","fid":"diaryPopup4","in":["ssCtx2"]}]}]}