{"stem":"danck","instances":[{"docUri":"1752.html","score":2,"contexts":[{"form":"Danck","weight":"1","pos":3364,"context":"...Ohren, und wir Nahmens mit großer Freude und <mark>Danck<\/mark> an, es befand sich alles sehr Wohl und Muntter...","fid":"diaryPopup32","in":["ssCtx2"]},{"form":"danck","weight":"1","pos":6001,"context":"...Fische im Waßer, und taußend Materien sonst zum <mark>danck<\/mark>, um 7 Uhr liefen wir in newyork ein,...","fid":"diaryPopup54","in":["ssCtx2"]}]},{"docUri":"1753atlantik.html","score":2,"contexts":[{"form":"Danck","weight":"1","pos":527,"context":" Den 11 ten Hatten wir zusammen ein <mark>Danck<\/mark>- Liebesmahl für alle Bewahrung die wir bis daher...","fid":"diaryPopup37","in":["ssCtx2"]},{"form":"Danck","weight":"1","pos":637,"context":"...ließ und gab ihnen Medicin Davor sie uns ein <mark>Danck<\/mark> Brod gaben welches uns sehr zu statten kam in...","fid":"diaryPopup48","in":["ssCtx2"]}]}]}