{"stem":"darnach","instances":[{"docUri":"1752.html","score":1,"contexts":[{"form":"darnach","weight":"1","pos":5189,"context":"...drüber haten, weil sie alle voll verlangen Waren <mark>darnach<\/mark>, mit den Brr. [Brüdern] redte...","fid":"diaryPopup48","in":["ssCtx2"]}]},{"docUri":"1742atlantik.html","score":1,"contexts":[{"form":"darnach","weight":"1","pos":2122,"context":"...daß wir konten das Land sehen und uns also <mark>darnach<\/mark> richten. Einmal waren wir im Nebel schon recht...","fid":"diaryPopup29"}]},{"docUri":"1749atlantik.html","score":1,"contexts":[{"form":"darnach","weight":"1","pos":3566,"context":"...sie nur ein wenig anrührete, so giengs Blut <mark>darnach<\/mark>. Solte Br Garrison mit seinem Schiffs Volck allein...","fid":"diaryPopup47"}]},{"docUri":"1746atlantik.html","score":1,"contexts":[{"form":"darnach","weight":"1","pos":11431,"context":"...wäre. Unsre Schiffs Leute verlangten auch alle sehr <mark>darnach<\/mark> weil es sehr kalt zu werden anfing und unsre...","fid":"diaryPopup63","in":["ssCtx2"]}]}]}