{"stem":"dateien","instances":[{"docUri":"einleitung.html","score":1,"contexts":[{"form":"Dateien","weight":"1","pos":719,"context":"...für alle Reiseberichte persistent verfügbare XML\/TEI-<mark>Dateien<\/mark> bereitgestellt, eine Suche integriert und der Code der...","in":["ssCtx1"]}]},{"docUri":"datenschutz.html","score":1,"contexts":[{"form":"Dateien","weight":"1","pos":650,"context":"...die Adresse und der Name der abgerufenen Webseiten und <mark>Dateien<\/mark>, Datum und Uhrzeit des Abrufs, übertragene Datenmengen...","in":["ssCtx1"]}]}]}