{"stem":"december","instances":[{"docUri":"1746atlantik.html","score":51,"contexts":[{"form":"December","weight":"2","pos":8727,"context":"<mark>December<\/mark> 1746","fid":"diaryPopup45"},{"form":"December","weight":"2","pos":8841,"context":"♀ Den 2ten <mark>December<\/mark>.","fid":"diaryPopup46"},{"form":"December","weight":"2","pos":8992,"context":"Sabbaths den 3ten <mark>December<\/mark>.","fid":"diaryPopup47"},{"form":"December","weight":"2","pos":9541,"context":"♂ Den 6ten <mark>December<\/mark>.","fid":"diaryPopup50"},{"form":"December","weight":"2","pos":9658,"context":"☿ Den 7ten <mark>December<\/mark>.","fid":"diaryPopup51"},{"form":"December","weight":"2","pos":9773,"context":"♃ Den 8ten <mark>December<\/mark>","fid":"diaryPopup52"},{"form":"December","weight":"2","pos":9895,"context":"♀ Den 9ten <mark>December<\/mark>.","fid":"diaryPopup53"},{"form":"December","weight":"2","pos":10042,"context":"Sabbaths den 10ten <mark>December<\/mark>.","fid":"diaryPopup54"},{"form":"December","weight":"2","pos":10172,"context":"☉ Den 11ten <mark>December<\/mark>.","fid":"diaryPopup55"},{"form":"December","weight":"2","pos":10306,"context":"☽ Den 12ten <mark>December<\/mark>.","fid":"diaryPopup56"},{"form":"December","weight":"2","pos":10423,"context":"♂ Den 13ten <mark>December<\/mark>.","fid":"diaryPopup57"},{"form":"December","weight":"2","pos":10599,"context":"☿ Den 14ten <mark>December<\/mark>.","fid":"diaryPopup58"},{"form":"December","weight":"2","pos":10754,"context":"♃ Den 15ten <mark>December<\/mark>.","fid":"diaryPopup59"},{"form":"December","weight":"2","pos":10944,"context":"♀ Den 16ten <mark>December<\/mark>.","fid":"diaryPopup60"},{"form":"December","weight":"2","pos":11083,"context":"Sabbaths den 17ten <mark>December<\/mark>.","fid":"diaryPopup61"},{"form":"December","weight":"2","pos":11227,"context":"☉ Den 18ten <mark>December<\/mark>.","fid":"diaryPopup62"},{"form":"December","weight":"2","pos":11368,"context":"☽ Den 19ten <mark>December<\/mark>.","fid":"diaryPopup63"},{"form":"December","weight":"2","pos":11646,"context":"♂ Den 20ten <mark>December<\/mark>.","fid":"diaryPopup64"},{"form":"December","weight":"2","pos":11786,"context":"☿ Den 21ten <mark>December<\/mark>","fid":"diaryPopup65"},{"form":"December","weight":"2","pos":11957,"context":"♃ Den 22ten <mark>December<\/mark>","fid":"diaryPopup66"},{"form":"December","weight":"2","pos":12173,"context":"♀ Den 23ten <mark>December<\/mark>.","fid":"diaryPopup67"},{"form":"December","weight":"2","pos":12335,"context":"Sabbaths den 24ten <mark>December<\/mark>.","fid":"diaryPopup68"},{"form":"December","weight":"2","pos":12566,"context":"☉ Den 25ten <mark>December<\/mark>.","fid":"diaryPopup69"},{"form":"December","weight":"2","pos":12727,"context":"☽ Den 26ten <mark>December<\/mark>.","fid":"diaryPopup70"},{"form":"December","weight":"2","pos":12992,"context":"♂ Den 27ten <mark>December<\/mark>.","fid":"diaryPopup71"},{"form":"December","weight":"1","pos":8585,"context":"...nach Philadelphia zu seegeln haben, und uns der <mark>December<\/mark> schon so nahe ist wir überließens aber doch ganz...","fid":"diaryPopup43","in":["ssCtx2"]}]},{"docUri":"1746amerika.html","score":6,"contexts":[{"form":"December","weight":"2","pos":74,"context":"☿ Den 28ten <mark>December<\/mark>.","fid":"diaryPopup1"},{"form":"December","weight":"2","pos":1011,"context":"♀ Den 30ten <mark>December<\/mark>.","fid":"diaryPopup3"},{"form":"December","weight":"2","pos":1335,"context":"♃ Den 31ten <mark>December<\/mark>.","fid":"diaryPopup4"}]}]}