{"stem":"empfinden","instances":[{"docUri":"1746atlantik.html","score":2,"contexts":[{"form":"empfinden","weight":"1","pos":8850,"context":"...und bey aller Hizze die wir von außen zu <mark>empfinden<\/mark> hatten, erfrischten wir uns in seinem blutgen Buß Kampfs...","fid":"diaryPopup46","in":["ssCtx2"]},{"form":"empfinden","weight":"1","pos":13080,"context":"...großen Kälte ziemlich anfingen ihre Ohnmacht und Schwächlichkeit zu <mark>empfinden<\/mark>.","fid":"diaryPopup71","in":["ssCtx2"]}]}]}