{"stem":"entzwey","instances":[{"docUri":"1761land.html","score":1,"contexts":[{"form":"entzwey","weight":"1","pos":2597,"context":"...vorder Axe an eine Säule und der Deistel ging <mark>entzwey<\/mark>. Wir mußten also noch ½ Stunde da seyn...","fid":"diaryPopup17","in":["ssCtx2"]}]},{"docUri":"1752.html","score":1,"contexts":[{"form":"entzwey","weight":"1","pos":3977,"context":"...die Treppe runter rolte, häte mir mein bein <mark>entzwey<\/mark> schlagen können, denn es fiel gerad auf mich,...","fid":"diaryPopup38","in":["ssCtx2"]}]},{"docUri":"1746atlantik.html","score":1,"contexts":[{"form":"entzwey","weight":"1","pos":10672,"context":"...an der einen Seite von oben biß unten durch <mark>entzwey<\/mark>; banden hernach unser Ruder an, und trieben nur...","fid":"diaryPopup58","in":["ssCtx2"]}]},{"docUri":"1746amerika.html","score":1,"contexts":[{"form":"entzwey","weight":"1","pos":2086,"context":"...auf den Weg, obschon das Eiß unsre Schuhe <mark>entzwey<\/mark> schnitte und wir Gefahr stunden unsre Füße zu verwunden...","fid":"diaryPopup7","in":["ssCtx2"]}]}]}