{"stem":"erkennen","instances":[{"docUri":"1746atlantik.html","score":2,"contexts":[{"form":"erkennen","weight":"1","pos":1668,"context":"...Gesichte sehr ferne von uns, konnten aber nicht <mark>erkennen<\/mark> was es war. Es hatte wenig Seegel auf...","fid":"diaryPopup1","in":["ssCtx2"]},{"form":"erkennen","weight":"1","pos":1914,"context":"...nahe an uns kam so gab Er sich zu <mark>erkennen<\/mark> daß er ein Englischer Man of War von 20...","fid":"diaryPopup1","in":["ssCtx2"]}]},{"docUri":"1761atlantik.html","score":2,"contexts":[{"form":"erkennen","weight":"1","pos":526,"context":"...lasen Abends die Rede. Sie sollen sich alle <mark>erkennen<\/mark>, beide klein u. groß.","fid":"diaryPopup7","in":["ssCtx2"]},{"form":"erkennen","weight":"1","pos":2742,"context":"...ten Stunde gab der Commodor durch seine Flagge zu <mark>erkennen<\/mark>, daß er Grund gefunden habe. Ey wie...","fid":"diaryPopup61","in":["ssCtx2"]}]},{"docUri":"1761kanal.html","score":2,"contexts":[{"form":"erkennen","weight":"1","pos":680,"context":"...-Schalupe zu kommen. Der Officier gab zu <mark>erkennen<\/mark>, daß er sie zwar nicht convoyren könne noch...","fid":"diaryPopup4","in":["ssCtx2"]},{"form":"erkennen","weight":"1","pos":824,"context":"...sie waren? Sie gaben sich aber nicht zu <mark>erkennen<\/mark>, u. sagten: sie brächten ihm einen Pilot...","fid":"diaryPopup4","in":["ssCtx2"]}]},{"docUri":"1752.html","score":1,"contexts":[{"form":"erkennen","weight":"1","pos":493,"context":"...recomandirte es sehr daß man daß doch ja recht <mark>erkennen<\/mark> solte, denn es sey eine solche erstaunliche große...","fid":"diaryPopup3","in":["ssCtx2"]}]}]}