{"stem":"erkennbar","instances":[{"docUri":"1752.html","score":1,"contexts":[{"form":"erkennbar","weight":"1","pos":37,"context":"...Tagespositionen des Schiffs zwischen im Tagebuch erwähnten Landmarken (<mark>erkennbar<\/mark> an den Richtungswechseln der Route) wieder. Klicken Sie...","fid":"HTUPopup","in":["ssCtx1"]}]},{"docUri":"1761atlantik.html","score":1,"contexts":[{"form":"erkennbar","weight":"1","pos":36,"context":"...Tagespositionen des Schiffs zwischen im Tagebuch erwähnten Landmarken (<mark>erkennbar<\/mark> an den Richtungswechseln der Route) wieder. Klicken Sie...","fid":"HTUPopup","in":["ssCtx1"]}]}]}