{"stem":"erwarteten","instances":[{"docUri":"1746atlantik.html","score":2,"contexts":[{"form":"erwarteten","weight":"1","pos":1836,"context":"...und ruhig hin, empfohlen uns unserm Lämmelein und <mark>erwarteten<\/mark> was geschehen würde. Es war uns recht artig...","fid":"diaryPopup1","in":["ssCtx2"]},{"form":"erwarteten","weight":"1","pos":2948,"context":"...Theil seines Leibes sind, zu seinen durchgrabenen Füßen und <mark>erwarteten<\/mark> seiner Flamm mit 100 Herzens Thränen. Er erfüllete...","fid":"diaryPopup6","in":["ssCtx2"]}]}]}