{"stem":"erzehlten","instances":[{"docUri":"1746amerika.html","score":2,"contexts":[{"form":"erzehlten","weight":"1","pos":1691,"context":"...vielen Freuden aufnahmen und viele Liebe erzeigten. Sie <mark>erzehlten<\/mark> uns daß auf der rechten Passage nach Dover wir...","fid":"diaryPopup5","in":["ssCtx2"]},{"form":"erzehlten","weight":"1","pos":1938,"context":"...wo wir bey recht hübschen Leuten logirten. Sie <mark>erzehlten<\/mark> uns daß jederman in Philadelphia glaube daß unser Schiff...","fid":"diaryPopup6","in":["ssCtx2"]}]}]}