{"stem":"fangen","instances":[{"docUri":"1753atlantik.html","score":2,"contexts":[{"form":"fangen","weight":"1","pos":335,"context":"...sehen, hatten auch das Vergnügen einen Dolphin zu <mark>fangen<\/mark>.","fid":"diaryPopup19","in":["ssCtx2"]},{"form":"fangen","weight":"1","pos":563,"context":"...hatten wir das Glück viele Fische Albekaws genannt zu <mark>fangen<\/mark> womit wir unsern Hunger zu Hülfe kamen. Auch...","fid":"diaryPopup47","in":["ssCtx2"]}]},{"docUri":"1761atlantik.html","score":1,"contexts":[{"form":"fangen","weight":"1","pos":1374,"context":"...von sich. Die Schiffs-Leute versuchten welche zu <mark>fangen<\/mark>, kriegten aber keine. Hingegen holte einer von...","fid":"diaryPopup21","in":["ssCtx2"]}]}]}