{"stem":"fragte","instances":[{"docUri":"1749atlantik.html","score":2,"contexts":[{"form":"fragte","weight":"1","pos":928,"context":"...und nach Nantes in Frankreich zurück kehrte. Es <mark>fragte<\/mark> uns um gute neue Zeitungen u. wir sagten ihnen...","fid":"diaryPopup18"},{"form":"fragte","weight":"1","pos":2727,"context":"...so Wetter gewesen: Die Judith die grönℓ. <mark>fragte<\/mark> heut Abend- [?] Singstund; man antwortete:...","fid":"diaryPopup36"}]},{"docUri":"1761nordsee.html","score":1,"contexts":[{"form":"fragte","weight":"1","pos":496,"context":"...Abend ein Engℓ. Kriegs-Schiff.(Man <mark>fragte<\/mark> uns, woher u. wohin ? Ob wir nicht...","fid":"diaryPopup5","in":["ssCtx2"]}]},{"docUri":"1746atlantik.html","score":1,"contexts":[{"form":"fragte","weight":"1","pos":1827,"context":"...Capitain von dem fremden Schiffe rief uns darauf an <mark>fragte<\/mark> erst wer wir wären zwar auf Englisch aber mit...","fid":"diaryPopup1","in":["ssCtx2"]}]},{"docUri":"1761kanal.html","score":1,"contexts":[{"form":"fragte","weight":"1","pos":809,"context":"...ist, gekommen, u. nun wieder zurückgeht. Er <mark>fragte<\/mark> unsern Captain, ob er nicht Mährℓ. Brr...","fid":"diaryPopup4"}]}]}