{"stem":"gebrauch","instances":[{"docUri":"1761land.html","score":1,"contexts":[{"form":"Gebrauch","weight":"1","pos":721,"context":"...u. Wachsstock gekauft, aber bis dato zu unserm <mark>Gebrauch<\/mark> nicht nöthig gehabt. Wir mußten also im Finstern...","fid":"diaryPopup3","in":["ssCtx2"]}]},{"docUri":"1742atlantik.html","score":1,"contexts":[{"form":"Gebrauch","weight":"1","pos":2130,"context":"...Die äußre Hütte müße auch noch stehen bleiben zum <mark>Gebrauch<\/mark>, es grüne unser Leben dir, u bringe...","fid":"diaryPopup29"}]},{"docUri":"impressum.html","score":1,"contexts":[{"form":"Gebrauch","weight":"1","pos":194,"context":"...Seite sind nur für den privaten, nicht kommerziellen <mark>Gebrauch<\/mark> gestattet.","in":["ssCtx1"]}]}]}