{"stem":"gelegt","instances":[{"docUri":"1746atlantik.html","score":2,"contexts":[{"form":"gelegt","weight":"1","pos":4576,"context":"...wenn der Geist des Kirchleins Philadelphia der auf uns <mark>gelegt<\/mark> ist, sich unter uns reget und unser Friedens Pläzgen...","fid":"diaryPopup15","in":["ssCtx2"]},{"form":"gelegt","weight":"1","pos":12787,"context":"...avanciret und hatten uns gegen Lewis Town vor Anker <mark>gelegt<\/mark> so fing der Wind wiederum an sehr hefftig aus...","fid":"diaryPopup70","in":["ssCtx2"]}]},{"docUri":"1746kanal.html","score":1,"contexts":[{"form":"gelegt","weight":"1","pos":1002,"context":"...deine Wohnung und hast dein Nest in den Felsen <mark>gelegt<\/mark>. Die heiligen 5 Wunden dein laß uns rechte...","fid":"diaryPopup4","in":["ssCtx2"]}]}]}