{"stem":"gesezt","instances":[{"docUri":"1761land.html","score":2,"contexts":[{"form":"gesezt","weight":"1","pos":1815,"context":"..., u. selbige wurde auf den 6ten feste <mark>gesezt<\/mark>.","fid":"diaryPopup10","in":["ssCtx2"]},{"form":"gesezt","weight":"1","pos":1840,"context":"...u. Brr. so mit den Fuhrwagen gehen feste <mark>gesezt<\/mark>. Es machte aber der Fehr Schreiber ohne der...","fid":"diaryPopup11","in":["ssCtx2"]}]},{"docUri":"1742amerika.html","score":2,"contexts":[{"form":"gesezt","weight":"1","pos":694,"context":"...waren mit Gutbefinden in den der übrigen ans Land <mark>gesezt<\/mark>, auf Long Island, damit sie nicht möchten...","fid":"diaryPopup1"},{"form":"gesezt","weight":"1","pos":1559,"context":"...-Tauesteeg. Hätte er d Ankher noch draußen <mark>gesezt<\/mark> so hätte es ihn in kl. Stücke geqwetscht....","fid":"diaryPopup5"}]},{"docUri":"1752.html","score":1,"contexts":[{"form":"gesezt","weight":"1","pos":1930,"context":"...Worüber wir beym auf-stehen in daß gröste vergnügen <mark>gesezt<\/mark> wurden, daß man sich nur vorstellen kan,...","fid":"diaryPopup17","in":["ssCtx2"]}]},{"docUri":"1746kanal.html","score":1,"contexts":[{"form":"gesezt","weight":"1","pos":683,"context":"...schon überall mitgetheilten Wunden des Lammes. Dazu ich <mark>gesezt<\/mark> bin ein Prediger κήρυξ. Wir ließen darauf auch...","fid":"diaryPopup2","in":["ssCtx2"]}]},{"docUri":"1742kanal.html","score":1,"contexts":[{"form":"gesezt","weight":"1","pos":417,"context":"...ihm nicht schweiget, biß daß Jerusalem gefertiget und <mark>gesezt<\/mark> werde zum Lobe auf Erden. Jes: 622...","fid":"diaryPopup3"}]}]}