{"stem":"gestorben","instances":[{"docUri":"1746atlantik.html","score":2,"contexts":[{"form":"gestorben","weight":"1","pos":7848,"context":"...Christ der du so willig bist an dem Creuz <mark>gestorben<\/mark> daß sie die Mutter ist hast du gewiß erworben...","fid":"diaryPopup38","in":["ssCtx2"]},{"form":"gestorben","weight":"1","pos":9794,"context":"...Christ der du so willig bist an dem Creuz <mark>gestorben<\/mark> und daß ein Bethlehem ist dem Herrnhut hast erworben...","fid":"diaryPopup52","in":["ssCtx2"]}]}]}