{"stem":"house","instances":[{"docUri":"1761kanal.html","score":3,"contexts":[{"form":"House","weight":"1","pos":271,"context":"...kurzen, aber besonders gesegneten Aufenthalt in Linsey-<mark>House<\/mark>, u. giengen zu Mittag nach zärtℓen Abschied,...","fid":"diaryPopup2","in":["ssCtx2"]},{"form":"House","weight":"1","pos":1744,"context":"...sondrℓ. in der lezten Versamlung in Lindsey-<mark>House<\/mark> hierüber erklärt hätte; doch wolle er die Geschw...","fid":"diaryPopup8","in":["ssCtx2"]},{"form":"House","weight":"1","pos":1887,"context":"...mit weinenden Augen nachsahen, wieder nach Lindsey-<mark>House<\/mark> zurück. Br. Nath. Marschall, Münster u....","fid":"diaryPopup8","in":["ssCtx2"]}]},{"docUri":"1761nordsee.html","score":2,"contexts":[{"form":"House","weight":"1","pos":622,"context":"...brachten unsre led. Brr. ins Lindsey-<mark>House<\/mark>. Br. Nathan. aber u. die übrigen Geschw...","fid":"diaryPopup8","in":["ssCtx2"]},{"form":"House","weight":"1","pos":653,"context":"..., doch ohne weitern Schaden. In Lindsey-<mark>House<\/mark> grüßte sich Abends voll Freude u. Dankbarkeit für die...","fid":"diaryPopup8","in":["ssCtx2"]}]}]}