{"stem":"höher","instances":[{"docUri":"1746atlantik.html","score":1,"contexts":[{"form":"höher","weight":"1","pos":10399,"context":"...die See fing auch an in dieser Gegend wieder <mark>höher<\/mark> zu gehen je weiter wir gegen Norden avancirten....","fid":"diaryPopup56","in":["ssCtx2"]}]},{"docUri":"1746amerika.html","score":1,"contexts":[{"form":"höher","weight":"1","pos":2897,"context":"...auf und hatten eine ziemlich beschwerliche Reise sonderlich je <mark>höher<\/mark> wir hinauf kamen weil wir wenig gebahnten Weg fanden...","fid":"diaryPopup14","in":["ssCtx2"]}]}]}