{"stem":"hübsch","instances":[{"docUri":"1752.html","score":2,"contexts":[{"form":"Hübsch","weight":"1","pos":3542,"context":"...es geweßen war, daß Wetter war auch ganz <mark>Hübsch<\/mark>, nur Offte Kleine Squals, die aber nichts...","fid":"diaryPopup34","in":["ssCtx2"]},{"form":"hübsch","weight":"1","pos":4662,"context":"...erfrischte sich recht daran, unser Wetter war ganz <mark>hübsch<\/mark>, der Wind schwach, wir besangen in unserer...","fid":"diaryPopup44","in":["ssCtx2"]}]},{"docUri":"1761nordsee.html","score":1,"contexts":[{"form":"hübsch","weight":"1","pos":371,"context":"...heute Vormitt. favorable wurde, so daß wir <mark>hübsch<\/mark> avancirten.","fid":"diaryPopup3","in":["ssCtx2"]}]},{"docUri":"1761kanal.html","score":1,"contexts":[{"form":"hübsch","weight":"1","pos":3362,"context":"...den Canal hinaus mit Freuden u. avancierten dieselbe Nacht <mark>hübsch<\/mark>.","fid":"diaryPopup11","in":["ssCtx2"]}]}]}