{"stem":"impressum","instances":[{"docUri":"search.html","score":1,"contexts":[{"form":"Impressum","weight":"1","pos":32,"context":" <mark>Impressum<\/mark> | Datenschutz "}]},{"docUri":"1746kanal.html","score":1,"contexts":[{"form":"Impressum","weight":"1","pos":3498,"context":" <mark>Impressum<\/mark> | Datenschutz "}]},{"docUri":"1746atlantik.html","score":1,"contexts":[{"form":"Impressum","weight":"1","pos":13106,"context":" <mark>Impressum<\/mark> | Datenschutz "}]},{"docUri":"1746amerika.html","score":1,"contexts":[{"form":"Impressum","weight":"1","pos":3094,"context":" <mark>Impressum<\/mark> | Datenschutz "}]},{"docUri":"index.html","score":1,"contexts":[{"form":"Impressum","weight":"1","pos":411,"context":" <mark>Impressum<\/mark> | Datenschutz "}]}]}