{"stem":"kontrolle","instances":[{"docUri":"datenschutz.html","score":1,"contexts":[{"form":"Kontrolle","weight":"1","pos":382,"context":"...der Vertraulichkeit, Integrität und Verfügbarkeit von Daten durch <mark>Kontrolle<\/mark> des physischen und elektronischen Zugangs zu den Daten als...","in":["ssCtx1"]}]},{"docUri":"impressum.html","score":1,"contexts":[{"form":"Kontrolle","weight":"1","pos":120,"context":"...Einfluss haben. Deshalb können wir trotz sorgfältiger inhaltlicher <mark>Kontrolle<\/mark> für diese fremden Inhalte auch keine Gewähr und Haftung...","in":["ssCtx1"]}]}]}