{"stem":"lag","instances":[{"docUri":"1746amerika.html","score":3,"contexts":[{"form":"lag","weight":"1","pos":788,"context":"...hineingefroren, dazu auch unser Boot welches am Lande <mark>lag<\/mark> eingefroren so daß wir just zur rechten Stunde vom...","fid":"diaryPopup2","in":["ssCtx2"]},{"form":"lag","weight":"1","pos":1192,"context":"...Allein die Bahn war ganz verschneyet, der Schnee <mark>lag<\/mark> aller Orten Knie hoch, die Nacht überfiel uns...","fid":"diaryPopup3","in":["ssCtx2"]},{"form":"lag","weight":"1","pos":2713,"context":"...alle so wohl und vergnügt hier angekommen; es <mark>lag<\/mark> auch ein Schiff fertig nach England abzugehen, weil...","fid":"diaryPopup11","in":["ssCtx2"]}]},{"docUri":"1752.html","score":1,"contexts":[{"form":"lag","weight":"1","pos":247,"context":"...auf Boaten biß Blakwall Alwo die Irene vor Ancker <mark>lag<\/mark> und sie erwartete, die Anna Antes wurde ihnen...","fid":"diaryPopup1","in":["ssCtx2"]}]},{"docUri":"einleitung.html","score":1,"contexts":[{"form":"lag","weight":"1","pos":66,"context":"...und neue Gemeinorte aufzubauen. Der Schwerpunkt der Aktivitäten <mark>lag<\/mark> in der atlantischen Welt.","fid":"introduction","in":["ssCtx1"]}]}]}