{"stem":"latit","instances":[{"docUri":"1746atlantik.html","score":3,"contexts":[{"form":"Latit","weight":"1","pos":9292,"context":"...i.l.[?] denen uns gegen Süden liegenden Islands in der <mark>Latit<\/mark>. von 17.18 Grad um Thomas und Crux herum...","fid":"diaryPopup49","in":["ssCtx2"]},{"form":"Latit","weight":"1","pos":9922,"context":"...flogen wir davon. Wir waren Mittags in der <mark>Latit<\/mark>. von 27 Grad 23 Min. und im...","fid":"diaryPopup53","in":["ssCtx2"]},{"form":"Latit","weight":"1","pos":12272,"context":"...so gnädig hindurchgebracht. Mittags waren wir in der <mark>Latit<\/mark>. von 38 Grad 17 Min. und also...","fid":"diaryPopup67","in":["ssCtx2"]}]},{"docUri":"1761atlantik.html","score":2,"contexts":[{"form":"Latit","weight":"1","pos":1552,"context":"...u. 10ten waren wir schon im 40 Grad <mark>Latit<\/mark>., ob wir gleich durch beständig anhaltende contraire Winde...","fid":"diaryPopup27","in":["ssCtx2"]},{"form":"Latit","weight":"1","pos":2506,"context":"...Longitude zu Ende seyn müste, u. in der <mark>Latit<\/mark>. einzubringen suchte, was wir zu weit südl...","fid":"diaryPopup54","in":["ssCtx2"]}]}]}