{"stem":"laße","instances":[{"docUri":"1742amerika.html","score":2,"contexts":[{"form":"laße","weight":"1","pos":1245,"context":"...sollen sie wohnen, wenn ich das Recht gehen <mark>laße<\/mark> über alle ihre Feinde um u. um; u. sollen...","fid":"diaryPopup4"},{"form":"laße","weight":"1","pos":1350,"context":"...ihre Steine u. Kalck zu gerichtet würden. Gott <mark>laße<\/mark> unser Flehen bey ihn erhöret seyn, daß nur...","fid":"diaryPopup5"}]},{"docUri":"1753amerika.html","score":1,"contexts":[{"form":"laße","weight":"1","pos":322,"context":"...jedes von uns auch den Lauff vollende, Er <mark>laße<\/mark> Seine Gnad u. Hülf über uns walten So können...","fid":"diaryPopup6"}]}]}