{"stem":"lindsey","instances":[{"docUri":"1761nordsee.html","score":2,"contexts":[{"form":"Lindsey","weight":"1","pos":673,"context":"..., u. brachten unsre led. Brr. ins <mark>Lindsey<\/mark>-House. Br. Nathan. aber u. die...","fid":"diaryPopup8","in":["ssCtx2"]},{"form":"Lindsey","weight":"1","pos":704,"context":"...übern haufen, doch ohne weitern Schaden. In <mark>Lindsey<\/mark>-House grüßte sich Abends voll Freude u. Dankbarkeit...","fid":"diaryPopup8","in":["ssCtx2"]}]},{"docUri":"1761kanal.html","score":2,"contexts":[{"form":"Lindsey","weight":"1","pos":1795,"context":"...mehrmalen u. sondrℓ. in der lezten Versamlung in <mark>Lindsey<\/mark>-House hierüber erklärt hätte; doch wolle er...","fid":"diaryPopup8"},{"form":"Lindsey","weight":"1","pos":1938,"context":"...die ihnen mit weinenden Augen nachsahen, wieder nach <mark>Lindsey<\/mark>-House zurück. Br. Nath. Marschall,...","fid":"diaryPopup8"}]}]}