{"stem":"october","instances":[{"docUri":"1752.html","score":62,"contexts":[{"form":"October","weight":"2","pos":595,"context":"<mark>October<\/mark>. Den 1sten","fid":"diaryPopup4","in":["ssCtx2"]},{"form":"October","weight":"2","pos":682,"context":"Montags den 2ten <mark>October<\/mark>","fid":"diaryPopup5","in":["ssCtx2"]},{"form":"October","weight":"2","pos":838,"context":"Dienstags den 3. <mark>October<\/mark>","fid":"diaryPopup6","in":["ssCtx2"]},{"form":"October","weight":"2","pos":962,"context":"Mitwochs den 4ten <mark>October<\/mark>","fid":"diaryPopup7","in":["ssCtx2"]},{"form":"October","weight":"2","pos":1085,"context":"Donnerstags den 5ten <mark>October<\/mark>","fid":"diaryPopup8","in":["ssCtx2"]},{"form":"October","weight":"2","pos":1219,"context":"Freytags den 6ten <mark>October<\/mark>","fid":"diaryPopup9","in":["ssCtx2"]},{"form":"October","weight":"2","pos":1282,"context":"Sabbaths den 7ten <mark>October<\/mark>","fid":"diaryPopup10","in":["ssCtx2"]},{"form":"October","weight":"2","pos":1365,"context":"Sonntags den 8ten <mark>October<\/mark>","fid":"diaryPopup11","in":["ssCtx2"]},{"form":"October","weight":"2","pos":1429,"context":"Montag den 9ten <mark>October<\/mark>","fid":"diaryPopup12","in":["ssCtx2"]},{"form":"October","weight":"2","pos":1495,"context":"Dienstag den 10ten <mark>October<\/mark>","fid":"diaryPopup13","in":["ssCtx2"]},{"form":"October","weight":"2","pos":1629,"context":"Mitwochs den 11ten <mark>October<\/mark>","fid":"diaryPopup14","in":["ssCtx2"]},{"form":"October","weight":"2","pos":1660,"context":"Donnerstags den 12ten <mark>October<\/mark>","fid":"diaryPopup15","in":["ssCtx2"]},{"form":"October","weight":"2","pos":1789,"context":"Freytags den 13ten <mark>October<\/mark>","fid":"diaryPopup16","in":["ssCtx2"]},{"form":"October","weight":"2","pos":1884,"context":"Sabbaths den 14ten <mark>October<\/mark>","fid":"diaryPopup17","in":["ssCtx2"]},{"form":"October","weight":"2","pos":2062,"context":"Sontag den 15ten <mark>October<\/mark>","fid":"diaryPopup18","in":["ssCtx2"]},{"form":"October","weight":"2","pos":2217,"context":"Montags den 16ten <mark>October<\/mark>","fid":"diaryPopup19","in":["ssCtx2"]},{"form":"October","weight":"2","pos":2296,"context":"Dienstag den 17ten <mark>October<\/mark>","fid":"diaryPopup20","in":["ssCtx2"]},{"form":"October","weight":"2","pos":2380,"context":"Mitwochs den 18ten <mark>October<\/mark>","fid":"diaryPopup21","in":["ssCtx2"]},{"form":"October","weight":"2","pos":2483,"context":"Donnerstag den 19ten <mark>October<\/mark>","fid":"diaryPopup22","in":["ssCtx2"]},{"form":"October","weight":"2","pos":2546,"context":"Freytag den 20ten <mark>October<\/mark>","fid":"diaryPopup23","in":["ssCtx2"]},{"form":"October","weight":"2","pos":2607,"context":"Sabbaths den 21ten <mark>October<\/mark>","fid":"diaryPopup24","in":["ssCtx2"]},{"form":"October","weight":"2","pos":2677,"context":"Sontags den 22ten <mark>October<\/mark>","fid":"diaryPopup25","in":["ssCtx2"]},{"form":"October","weight":"2","pos":2785,"context":"Montag den 23ten <mark>October<\/mark>","fid":"diaryPopup26","in":["ssCtx2"]},{"form":"October","weight":"2","pos":2839,"context":"Dienstag den 24ten <mark>October<\/mark>","fid":"diaryPopup27","in":["ssCtx2"]},{"form":"October","weight":"2","pos":2912,"context":"Mitwoch den 25ten <mark>October<\/mark>","fid":"diaryPopup28","in":["ssCtx2"]},{"form":"October","weight":"2","pos":2982,"context":"Donnerstag den 26ten <mark>October<\/mark>","fid":"diaryPopup29","in":["ssCtx2"]},{"form":"October","weight":"2","pos":3085,"context":"Freytag den 27ten <mark>October<\/mark>","fid":"diaryPopup30","in":["ssCtx2"]},{"form":"October","weight":"2","pos":3183,"context":"Sabbaths den 28ten <mark>October<\/mark>","fid":"diaryPopup31","in":["ssCtx2"]},{"form":"October","weight":"2","pos":3262,"context":"Sontags den 29ten <mark>October<\/mark>","fid":"diaryPopup32","in":["ssCtx2"]},{"form":"October","weight":"2","pos":3348,"context":"Montags den 30ten <mark>October<\/mark>","fid":"diaryPopup33","in":["ssCtx2"]},{"form":"October","weight":"2","pos":3467,"context":"Dienstag den 31ten <mark>October<\/mark>","fid":"diaryPopup34","in":["ssCtx2"]}]},{"docUri":"1746kanal.html","score":2,"contexts":[{"form":"October","weight":"2","pos":1317,"context":"<mark>October<\/mark>. 1746. ♄ Den 1ten Octobr....","fid":"diaryPopup6","in":["ssCtx2"]}]}]}