{"stem":"ruhe","instances":[{"docUri":"1746atlantik.html","score":2,"contexts":[{"form":"Ruhe","weight":"1","pos":2303,"context":"...Hieß unsre Loosung: Der Herr hat seinem Volk <mark>Ruhe<\/mark> gegeben und siegelt es der Sünde nu und aller...","fid":"diaryPopup3","in":["ssCtx2"]},{"form":"Ruhe","weight":"1","pos":4684,"context":"...Loosung hieß mit Recht: Das Lämmlein das uns <mark>Ruhe<\/mark> bringt mit seinem eignen Blute ist werth daß ihrs...","fid":"diaryPopup16","in":["ssCtx2"]}]},{"docUri":"1746amerika.html","score":1,"contexts":[{"form":"Ruhe","weight":"1","pos":3047,"context":"...daß wir nach so langem Warten endlich einmal unser <mark>Ruhe<\/mark> Pläzchen gefunden, und das Lammes Volck in Bethlehem...","fid":"diaryPopup16","in":["ssCtx2"]}]}]}