{"stem":"schlagen","instances":[{"docUri":"1761land.html","score":1,"contexts":[{"form":"schlagen","weight":"1","pos":672,"context":"...verschloßen. Und ich stieg herunter und wollte Feuer <mark>schlagen<\/mark>, verlor aber mein Stahl den ich in den...","fid":"diaryPopup3","in":["ssCtx2"]}]},{"docUri":"1752.html","score":1,"contexts":[{"form":"schlagen","weight":"1","pos":3954,"context":"...Treppe runter rolte, häte mir mein bein entzwey <mark>schlagen<\/mark> können, denn es fiel gerad auf mich, und...","fid":"diaryPopup38","in":["ssCtx2"]}]}]}