{"stem":"seereisen","instances":[{"docUri":"einleitung.html","score":4,"contexts":[{"form":"Seereisen","weight":"2","pos":2,"context":"Zu den <mark>Seereisen<\/mark> der Herrnhuter Brüdergemeine","fid":"introduction","in":["ssCtx1"]},{"form":"Seereisen","weight":"2","pos":689,"context":"Weiterführende Literatur zu Herrnhuter <mark>Seereisen<\/mark> und zum Projekt","fid":"introduction","in":["ssCtx1"]}]},{"docUri":"index.html","score":2,"contexts":[{"form":"Seereisen","weight":"2","pos":6,"context":"Das Portal zur Erkundung Herrnhuter <mark>Seereisen<\/mark> des 18. Jahrhunderts"}]}]}