{"stem":"sept","instances":[{"docUri":"1752.html","score":2,"contexts":[{"form":"Sept","weight":"1","pos":341,"context":"Freytag d[en] 29ten <mark>Sept<\/mark>[e]m.[ber] Früh wurden die Ancker gelichtet,...","fid":"diaryPopup2","in":["ssCtx2"]},{"form":"Sept","weight":"1","pos":397,"context":"Sabbaths d[en] 30ten <mark>Sept<\/mark>[e]m.[ber] ruheten sie und erwarteten Papagen und...","fid":"diaryPopup3","in":["ssCtx2"]}]},{"docUri":"einleitung.html","score":1,"contexts":[{"form":"Sept","weight":"1","pos":679,"context":"...u. Br. Töltschig von London nach Bethlehem. 28. <mark>Sept<\/mark>. bis 25. Nov. 1752.\" aus dem...","in":["ssCtx1"]}]}]}