{"stem":"stimmten","instances":[{"docUri":"1749atlantik.html","score":2,"contexts":[{"form":"stimmten","weight":"1","pos":2400,"context":"...früh als am Ostertage bey der Sonnen-Aufgang <mark>stimmten<\/mark> unsere Musici dem auferstandenen Heiland auf der Decke manche...","fid":"diaryPopup29"},{"form":"stimmten","weight":"1","pos":3244,"context":"...ihres Lieben Herzels Rubuscho an seinem heutigen Geburtstag u. <mark>stimmten<\/mark> mit Music ihme manche recht gefühlige Versel an. Der...","fid":"diaryPopup43"}]}]}