{"stem":"texel","instances":[{"docUri":"1761nordsee.html","score":2,"contexts":[{"form":"Texel","weight":"1","pos":375,"context":"d 8 t erreichten wir Vormittags <mark>Texel<\/mark>, der Wind wurde contrair. Wir lavirten bis...","fid":"diaryPopup4","in":["ssCtx2"]},{"form":"Texel","weight":"1","pos":424,"context":"...guten HErrn für seine sonderbare hülfe; denn wem <mark>Texel<\/mark> bekannt ist, der weiß, was es ist, da...","fid":"diaryPopup4","in":["ssCtx2"]}]},{"docUri":"1761kanal.html","score":1,"contexts":[{"form":"Texel","weight":"1","pos":820,"context":"...Reise aus Holland ereignete: Als sie Abends von <mark>Texel<\/mark> herausfuhren, entdeckten sie von fernen ein Boot,...","fid":"diaryPopup4","in":["ssCtx2"]}]}]}