{"stem":"unsrem","instances":[{"docUri":"1746kanal.html","score":1,"contexts":[{"form":"unsrem","weight":"1","pos":2750,"context":"...und unter einander hätte stöhren können; legten uns alle <mark>unsrem<\/mark> Lamme zu Füßen weinten vor Gebrech und Fehl nach...","fid":"diaryPopup17","in":["ssCtx2"]}]},{"docUri":"1746atlantik.html","score":1,"contexts":[{"form":"unsrem","weight":"1","pos":1825,"context":"...sie zuerst greiffen sollten. Wir kamen alle in <mark>unsrem<\/mark> Pläzgen hinter dem Vorhang zusammen, blieben zum Theil...","fid":"diaryPopup1","in":["ssCtx2"]}]}]}