{"stem":"ursach","instances":[{"docUri":"1746amerika.html","score":2,"contexts":[{"form":"Ursach","weight":"1","pos":1006,"context":"...wir glaubten gewiß unser Lämmlein hat uns nicht ohne <mark>Ursach<\/mark> nach Lewistown kommen laßen.","fid":"diaryPopup2","in":["ssCtx2"]},{"form":"Ursach","weight":"1","pos":1714,"context":"...schwerlich durchkommen können daß es also wohl nicht ohne <mark>Ursach<\/mark> geschehen daß wir uns verirret. Mittags um 1...","fid":"diaryPopup5","in":["ssCtx2"]}]}]}