{"stem":"verfahren","instances":[{"docUri":"datenschutz.html","score":3,"contexts":[{"form":"Verfahren","weight":"1","pos":397,"context":"...Verfügbarkeit und ihrer Trennung. Des Weiteren haben wir <mark>Verfahren<\/mark> eingerichtet, die eine Wahrnehmung von Betroffenenrechten, die...","in":["ssCtx1"]},{"form":"Verfahren","weight":"1","pos":418,"context":"...Entwicklung bzw. Auswahl von Hardware, Software sowie <mark>Verfahren<\/mark> entsprechend dem Prinzip des Datenschutzes, durch Technikgestaltung und...","in":["ssCtx1"]},{"form":"Verfahren","weight":"1","pos":607,"context":"Weitere Hinweise zu Verarbeitungsprozessen, <mark>Verfahren<\/mark> und Diensten:","in":["ssCtx1"]}]}]}