{"stem":"vermuthℓ","instances":[{"docUri":"1749atlantik.html","score":2,"contexts":[{"form":"vermuthℓ","weight":"1","pos":820,"context":"..., das seinen Cours nach Engelland nahm, u. <mark>vermuthℓ<\/mark> wie unsere Leute wehnten von Neuyorck kam. Es...","fid":"diaryPopup15"},{"form":"vermuthℓ","weight":"1","pos":1831,"context":"...heute wieder ein Schiff uns entgegen kommen, das <mark>vermuthℓ<\/mark>. nach Madera gegangen wie unser Schiffs Leute sagten...","fid":"diaryPopup26"}]},{"docUri":"1761nordsee.html","score":1,"contexts":[{"form":"vermuthℓ","weight":"1","pos":559,"context":"...uns zu, u. weil unser Top-Segel, <mark>vermuthℓ<\/mark>. aus Vergeßenheit, nicht eingezogen war, so...","fid":"diaryPopup7","in":["ssCtx2"]}]},{"docUri":"1761atlantik.html","score":1,"contexts":[{"form":"vermuthℓ","weight":"1","pos":507,"context":"...aber auch zugleich die halbe Flotte verloren, welches <mark>vermuthℓ<\/mark>. gestern Abend bey der Aenderung unseres Courses muß...","fid":"diaryPopup7","in":["ssCtx2"]}]},{"docUri":"1761kanal.html","score":1,"contexts":[{"form":"vermuthℓ","weight":"1","pos":3712,"context":"...ten segelte uns ein großes Dänisches Schiff, das <mark>vermuthℓ<\/mark>. von Ost-Indien zurück kam, vorbey...","fid":"diaryPopup14"}]}]}