{"stem":"vertrauen","instances":[{"docUri":"1746kanal.html","score":1,"contexts":[{"form":"Vertrauen","weight":"1","pos":3128,"context":"..., und hatten zu unserm lieben Vater das kindliche <mark>Vertrauen<\/mark> er würde uns auch beides auf unsrer Reise erfahren...","fid":"diaryPopup21","in":["ssCtx2"]}]},{"docUri":"1746atlantik.html","score":1,"contexts":[{"form":"vertrauen","weight":"1","pos":9337,"context":"...Beweise deine wunderliche Güte du Heiland derer die dir <mark>vertrauen<\/mark> Gebeut[?] uns daß wir glücklich seyn. Wir...","fid":"diaryPopup49","in":["ssCtx2"]}]}]}