{"stem":"wagens","instances":[{"docUri":"1761land.html","score":2,"contexts":[{"form":"Wagens","weight":"1","pos":1245,"context":"...daß die Personen hinüber über die Elbe kommen die <mark>Wagens<\/mark> aber dorten bleiben mußten. Er sagte auch daß...","fid":"diaryPopup6","in":["ssCtx2"]},{"form":"Wagens","weight":"1","pos":1759,"context":".... so mit den Fruchtewagen kommen. Ihre zwey <mark>Wagens<\/mark> ließen sie mit den Fuhrleuten in Jüterklik zwischen Zerbst...","fid":"diaryPopup9","in":["ssCtx2"]}]}]}