{"stem":"wahnert","instances":[{"docUri":"1742atlantik.html","score":1,"contexts":[{"form":"Wahnert","weight":"1","pos":194,"context":"...Persohnen ganz wohl, unter welchen unser Koch Br: <mark>Wahnert<\/mark>, u seine Frau welche Krankenwärterin, u sich...","fid":"diaryPopup1"}]},{"docUri":"1761kanal.html","score":1,"contexts":[{"form":"Wahnert","weight":"1","pos":1376,"context":"...in den Gelegenheiten, u. dem Br. Arboe u. <mark>Wahnert<\/mark> die äußere Besorgung der Brr. ins Ganze unter...","fid":"diaryPopup8"}]}]}