{"stem":"warn","instances":[{"docUri":"1746atlantik.html","score":3,"contexts":[{"form":"warn","weight":"1","pos":2170,"context":".... Unser Cours war West Süd West und wir <mark>warn<\/mark> gegen Abend zwischen dem 46 und 47ten Grad...","fid":"diaryPopup2","in":["ssCtx2"]},{"form":"warn","weight":"1","pos":3709,"context":"...Loosung: Liebet den Herrn alle seine Heilige wir <mark>warn<\/mark> alle Sünder im großen Grade und darum haben wir...","fid":"diaryPopup10","in":["ssCtx2"]},{"form":"warn","weight":"1","pos":3760,"context":"...Europa und kamen in die Africanische See, und <mark>warn<\/mark> Mittags in der Breite von 35 Grad 17 Min...","fid":"diaryPopup10","in":["ssCtx2"]}]}]}