{"stem":"well","instances":[{"docUri":"1746atlantik.html","score":3,"contexts":[{"form":"Well","weight":"1","pos":7408,"context":"...Americanschen Meer und hat wohl noch durch Fluth und <mark>Well<\/mark> 500 Meilen biß zur Stell zur Ruh im Kirchen...","fid":"diaryPopup35","in":["ssCtx2"]},{"form":"Well","weight":"1","pos":9496,"context":"...Revir was war uns so erquicklich so angenehm bey <mark>Well<\/mark> und Fluth bey Wind und schwerer Hizze? Das...","fid":"diaryPopup49","in":["ssCtx2"]},{"form":"Well","weight":"1","pos":10749,"context":"...sind, und Er uns durch Sturm und Wind und <mark>Well<\/mark> wohl zur Stelle helffen wird.","fid":"diaryPopup58","in":["ssCtx2"]}]}]}